simple_recorder-0.5.0.dist-info/METADATA
simple_recorder-0.5.0.dist-info/WHEEL
simple_recorder-0.5.0.dist-info/entry_points.txt
simple_recorder/__init__.py
simple_recorder/chapter.py
simple_recorder/cli.py
simple_recorder/directory.py
simple_recorder/errors.py
simple_recorder/gui.py
simple_recorder/pause.py
simple_recorder/resume.py
simple_recorder/split.py
simple_recorder/start.py
simple_recorder/stop.py
simple_recorder/styler.py
simple_recorder-0.5.0.dist-info/RECORD
