Metadata-Version: 2.1
Name: simple-recorder
Version: 0.5.0
Summary: A simple OBS recorder
Author-Email: onyx-and-iris <code@onyxandiris.online>
License: MIT
Requires-Python: >=3.11
Requires-Dist: clypi>=1.8.1
Requires-Dist: FreeSimpleGUI>=5.2.0.post1
Requires-Dist: obsws-python>=1.8.0
